PyRsa/__init__.py
PyRsa/pyb64.py
PyRsa/pyjsbn.py
PyRsa/pyrng.py
PyRsa/pyrsa.py
PyRsa/tools.py
PyRsa-1.0.3.dist-info/LICENSE
PyRsa-1.0.3.dist-info/METADATA
PyRsa-1.0.3.dist-info/WHEEL
PyRsa-1.0.3.dist-info/entry_points.txt
PyRsa-1.0.3.dist-info/top_level.txt
PyRsa-1.0.3.dist-info/RECORD
