Metadata-Version: 2.1
Name: PyRsa
Version: 1.0.3
Summary: python enables rsa encryption
Home-page: https://github.com/hibiscustoyou/pyrsa
Author: 张协涛
Author-email: zxt502838517@gmail.com
License: UNKNOWN
Platform: UNKNOWN
Classifier: Programming Language :: Python :: 3
Classifier: License :: OSI Approved :: MIT License
Classifier: Operating System :: OS Independent
